tc_pdf/__init__.py
tc_pdf/pdf.py
tc_pdf/handlers/__init__.py
tc_pdf/handlers/pdf.py
tc_pdf-0.0.7.dist-info/DESCRIPTION.rst
tc_pdf-0.0.7.dist-info/METADATA
tc_pdf-0.0.7.dist-info/RECORD
tc_pdf-0.0.7.dist-info/WHEEL
tc_pdf-0.0.7.dist-info/metadata.json
tc_pdf-0.0.7.dist-info/top_level.txt
