Metadata-Version: 2.0
Name: tc-pdf
Version: 0.0.7
Summary: PDF Preview
Home-page: http://github.com/intellisense/tc_pdf
Author: Aamir Rind
Author-email: aamir.adnan.rind@gmail.com
License: MIT
Platform: any
Classifier: Development Status :: 4 - Beta
Classifier: Intended Audience :: Developers
Classifier: License :: OSI Approved :: MIT License
Classifier: Operating System :: OS Independent
Classifier: Programming Language :: Python
Classifier: Topic :: Software Development :: Libraries :: Python Modules
Requires-Dist: libthumbor
Requires-Dist: tc-core
Requires-Dist: thumbor
Requires-Dist: tornado
Requires-Dist: Wand
Provides-Extra: tests
Requires-Dist: coverage; extra == 'tests'
